Starting compilation of: Hanoi.grace
Parsing...
Semantic analysis...
// class version 49.0 (49)
// access flags 0x1
public class MiniBasic {

  // compiled from: MiniBasic.in

  // access flags 0x9
  public static [I theVars

  // access flags 0x9
  public static move(Ljava/lang/String;Ljava/lang/String;)V
    GETSTATIC java/lang/System.out : Ljava/io/PrintStream;
    LDC "Rings: "
    INVOKEVIRTUAL java/io/PrintStream.println (Ljava/lang/String;)V
    GETSTATIC MiniBasic.theVars : [I
    BIPUSH -19
    BIPUSH 3
    IASTORE
    GETSTATIC MiniBasic.theVars : [I
    BIPUSH -19
    IALOAD
    LDC "left"
    LDC "right"
    LDC "middle"
    INVOKESTATIC MiniBasic.hanoi (ILjava/lang/String;Ljava/lang/String;Ljava/lang/String;)V
    RETURN
    MAXSTACK = 128
    MAXLOCALS = 3

  // access flags 0x9
  public static hanoi(ILjava/lang/String;Ljava/lang/String;Ljava/lang/String;)V
    GETSTATIC MiniBasic.theVars : [I
    BIPUSH 17
    IALOAD
    ICONST_1
    IF_ICMPGE L0
    ICONST_0
    GOTO L1
   L0
    ICONST_1
   L1
    IFEQ L2
    GETSTATIC MiniBasic.theVars : [I
    BIPUSH 17
    IALOAD
    ICONST_1
    ISUB
    GETSTATIC MiniBasic.theVars : [I
    BIPUSH 18
    IALOAD
    GETSTATIC MiniBasic.theVars : [I
    BIPUSH 0
    IALOAD
    GETSTATIC MiniBasic.theVars : [I
    BIPUSH 19
    IALOAD
    INVOKESTATIC MiniBasic.hanoi (IIII)V
    GETSTATIC MiniBasic.theVars : [I
    BIPUSH 18
    IALOAD
    GETSTATIC MiniBasic.theVars : [I
    BIPUSH 19
    IALOAD
    INVOKESTATIC MiniBasic.move (II)V
    GETSTATIC MiniBasic.theVars : [I
    BIPUSH 17
    IALOAD
    ICONST_1
    ISUB
    GETSTATIC MiniBasic.theVars : [I
    BIPUSH 0
    IALOAD
    GETSTATIC MiniBasic.theVars : [I
    BIPUSH 19
    IALOAD
    GETSTATIC MiniBasic.theVars : [I
    BIPUSH 18
    IALOAD
    INVOKESTATIC MiniBasic.hanoi (IIII)V
    GOTO L3
   L2
   L3
    RETURN
    MAXSTACK = 128
    MAXLOCALS = 5

  // access flags 0x9
  public static solve()V
    GETSTATIC java/lang/System.out : Ljava/io/PrintStream;
    LDC "Moving from "
    INVOKEVIRTUAL java/io/PrintStream.println (Ljava/lang/String;)V
    GETSTATIC java/lang/System.out : Ljava/io/PrintStream;
    GETSTATIC MiniBasic.theVars : [I
    BIPUSH 18
    IALOAD
    INVOKEVIRTUAL java/io/PrintStream.println (I)V
    GETSTATIC java/lang/System.out : Ljava/io/PrintStream;
    LDC " to "
    INVOKEVIRTUAL java/io/PrintStream.println (Ljava/lang/String;)V
    GETSTATIC java/lang/System.out : Ljava/io/PrintStream;
    GETSTATIC MiniBasic.theVars : [I
    BIPUSH 19
    IALOAD
    INVOKEVIRTUAL java/io/PrintStream.println (I)V
    GETSTATIC java/lang/System.out : Ljava/io/PrintStream;
    LDC ".\\n"
    INVOKEVIRTUAL java/io/PrintStream.println (Ljava/lang/String;)V
    RETURN
    MAXSTACK = 128
    MAXLOCALS = 1

  // access flags 0x9
  public static main()V
    INVOKESTATIC MiniBasic.solve ()V
    RETURN
    MAXSTACK = 128
    MAXLOCALS = 1

  // access flags 0x9
  public static main([Ljava/lang/String;)V
    INVOKESTATIC MiniBasic.main ()V
    RETURN
    MAXSTACK = 128
    MAXLOCALS = 1
}
Compilation successful
